{
  "date": "2026-03-24",
  "total_amount": 20960.699571219997,
  "total_volume": 1418360592.77,
  "up_count": 5136,
  "down_count": 329,
  "flat_count": 16,
  "limit_up_count": 133,
  "limit_down_count": 1,
  "north_flow": 0.0,
  "indices": [
    {
      "code": "sh000001",
      "name": "上证指数",
      "current": 3881.2797,
      "change": 67.997,
      "change_pct": 1.783,
      "open": 3849.6312,
      "high": 3881.4236,
      "low": 3807.9937,
      "prev_close": 3813.2829,
      "volume": 680622039.0,
      "amount": 931418842711.0,
      "amplitude": 1.9256347332635637
    },
    {
      "code": "sz399001",
      "name": "深证成指",
      "current": 13536.556,
      "change": 191.042,
      "change_pct": 1.432,
      "open": 13514.67,
      "high": 13536.556,
      "low": 13169.251,
      "prev_close": 13345.514,
      "volume": 73071623317.0,
      "amount": 1151421880430.0,
      "amplitude": 2.752273160853904
    },
    {
      "code": "sz399006",
      "name": "创业板指",
      "current": 3251.545,
      "change": 16.324,
      "change_pct": 0.505,
      "open": 3266.932,
      "high": 3270.191,
      "low": 3155.271,
      "prev_close": 3235.221,
      "volume": 20522547863.0,
      "amount": 515432678298.0,
      "amplitude": 3.5521530059306494
    },
    {
      "code": "sh000688",
      "name": "科创50",
      "current": 1290.7912,
      "change": 29.353,
      "change_pct": 2.327,
      "open": 1281.579,
      "high": 1291.9183,
      "low": 1249.0112,
      "prev_close": 1261.4377,
      "volume": 11716630.0,
      "amount": 67331736609.0,
      "amplitude": 3.4014442409641106
    },
    {
      "code": "sh000016",
      "name": "上证50",
      "current": 2830.854,
      "change": 38.525,
      "change_pct": 1.38,
      "open": 2813.4977,
      "high": 2831.2721,
      "low": 2790.8032,
      "prev_close": 2792.3288,
      "volume": 63312736.0,
      "amount": 135732067710.0,
      "amplitude": 1.449288493532721
    },
    {
      "code": "sh000300",
      "name": "沪深300",
      "current": 4474.7224,
      "change": 56.725,
      "change_pct": 1.284,
      "open": 4458.9074,
      "high": 4474.825,
      "low": 4394.2943,
      "prev_close": 4417.9971,
      "volume": 255532517.0,
      "amount": 530149390314.0,
      "amplitude": 1.8227875251434698
    }
  ],
  "top_sectors": [],
  "bottom_sectors": []
}